lite_sort-0.1.3.dist-info/licenses/LICENSE
litesort/__init__.py
litesort/argparse.py
litesort/config.py
litesort/filetype.py
litesort/main.py
litesort/utils.py
lite_sort-0.1.3.dist-info/METADATA
lite_sort-0.1.3.dist-info/WHEEL
lite_sort-0.1.3.dist-info/entry_points.txt
lite_sort-0.1.3.dist-info/top_level.txt
lite_sort-0.1.3.dist-info/RECORD
