Metadata-Version: 2.4
Name: lite-sort
Version: 0.1.3
Summary: Sort/group files by their file-type
Maintainer-email: Saheed Adeleye <aadesaed@gmail.com>
License-Expression: MPL-2.0
Project-URL: Repository, https://github.com/gyreas/lite-sort
Keywords: file,directory,file_manipulation,filesort,mime
Requires-Python: >=3.10
License-File: LICENSE
Requires-Dist: pytest>=8.3.5
Requires-Dist: python-magic==0.4.27
Dynamic: license-file
